shh/__init__.py
shh/__main__.py
shh/hidden_service.py
shh/utils.py
shh-0.0.1.dist-info/DESCRIPTION.rst
shh-0.0.1.dist-info/METADATA
shh-0.0.1.dist-info/RECORD
shh-0.0.1.dist-info/WHEEL
shh-0.0.1.dist-info/metadata.json
shh-0.0.1.dist-info/top_level.txt
