Metadata-Version: 2.0
Name: shh
Version: 0.0.1
Summary: Making Tor hidden services easy
Home-page: https://github.com/wybiral/shh/
Author: Davy Wybiral
Author-email: davy.wybiral@gmail.com
License: UNKNOWN
Platform: any
Requires-Dist: stem (==1.4.0)
